{
	"type": "minecraft:block",
	"pools": [
		{
			"rolls": 1,
			"entries": [
				{
					"type": "minecraft:item",
					"name": "minecraft:bowl"
				}
			],
			"conditions": [
				{
					"condition": "minecraft:inverted",
					"term": {
						"condition": "minecraft:block_state_property",
						"block": "ktfcc:cold_style_sashimi",
						"properties": {
							"bites": "0"
						}
					}
				}
			]
		},
		{
			"rolls": 2,
			"entries": [
				{
					"type": "minecraft:item",
					"name": "minecraft:snowball"
				}
			],
			"conditions": [
				{
					"condition": "minecraft:inverted",
					"term": {
						"condition": "minecraft:block_state_property",
						"block": "ktfcc:cold_style_sashimi",
						"properties": {
							"bites": "0"
						}
					}
				}
			]
		}
	],
	"random_sequence": "ktfcc:blocks/cold_style_sashimi"
}